redmine_mcp_server/__init__.py
redmine_mcp_server/server.py
xukaaaa_redmine_mcp-0.1.4.dist-info/METADATA
xukaaaa_redmine_mcp-0.1.4.dist-info/WHEEL
xukaaaa_redmine_mcp-0.1.4.dist-info/entry_points.txt
xukaaaa_redmine_mcp-0.1.4.dist-info/licenses/LICENSE
xukaaaa_redmine_mcp-0.1.4.dist-info/RECORD
