Metadata-Version: 2.4
Name: xukaaaa-redmine-mcp
Version: 0.1.4
Summary: MCP Server for Redmine - Manage tasks, log time, update status via Claude/AI assistants
Project-URL: Homepage, https://github.com/xukaaaa/redmine-mcp-server
Project-URL: Repository, https://github.com/xukaaaa/redmine-mcp-server
Project-URL: Issues, https://github.com/xukaaaa/redmine-mcp-server/issues
Author-email: xukaaaa <18020331@vnu.edu.vn>
License: MIT
License-File: LICENSE
Keywords: ai,automation,claude,mcp,project-management,redmine
Classifier: Development Status :: 4 - Beta
Classifier: Intended Audience :: Developers
Classifier: License :: OSI Approved :: MIT License
Classifier: Programming Language :: Python :: 3
Classifier: Programming Language :: Python :: 3.10
Classifier: Programming Language :: Python :: 3.11
Classifier: Programming Language :: Python :: 3.12
Requires-Python: >=3.10
Requires-Dist: mcp>=1.0.0
